<layer>
  <name>qgis_irmt_61244607_617c_425e_bb3c_81e06d3ef5e6</name>
  <id>LayerInfoImpl--56cfc338:16a2aa3373a:-7efe</id>
  <type>VECTOR</type>
  <defaultStyle>
    <id>StyleInfoImpl--56cfc338:16a2aa3373a:-7fb9</id>
  </defaultStyle>
  <resource class="featureType">
    <id>FeatureTypeInfoImpl--56cfc338:16a2aa3373a:-7f00</id>
  </resource>
  <queryable>true</queryable>
  <opaque>false</opaque>
  <attribution>
    <title>MTOQUICA</title>
    <logoWidth>0</logoWidth>
    <logoHeight>0</logoHeight>
  </attribution>
</layer>